payu_api
