Metadata-Version: 2.1
Name: django-payu-api
Version: 1.0.6
Summary: PayU API is a solution that allows you to make payments through the PayU payment gateway.
Home-page: https://gitlab.com/integree/payu_api
Author: Integree Bussines Solutions
Author-email: hello@integree.eu
License: UNKNOWN
Platform: UNKNOWN
Classifier: Development Status :: 5 - Production/Stable
Classifier: Intended Audience :: Developers
Classifier: Operating System :: OS Independent
Classifier: Environment :: Web Environment
Classifier: Programming Language :: Python :: 3.6
Classifier: Programming Language :: Python :: 2.7
Classifier: Framework :: Django :: 1.11
Classifier: Framework :: Django :: 2.0
Classifier: License :: OSI Approved :: MIT License
